{"duration":16,"measures":[{"type":"measure","time":0,"number":1},{"type":"measure","time":1,"number":2},{"type":"measure","time":2,"number":3},{"type":"measure","time":3,"number":4},{"type":"measure","time":4,"number":5},{"type":"measure","time":5,"number":6},{"type":"measure","time":6,"number":7},{"type":"measure","time":7,"number":8},{"type":"measure","time":8,"number":9},{"type":"measure","time":9,"number":10},{"type":"measure","time":10,"number":11},{"type":"measure","time":11,"number":12},{"type":"measure","time":12,"number":13},{"type":"measure","time":13,"number":14},{"type":"measure","time":14,"number":15},{"type":"measure","time":15.497916666666667,"number":16}],"notes":[{"type":"note","time":0,"duration":0.4979166666666667,"noteValue":46,"track":1,"pitch":{"octave":4,"step":"G","alter":0},"accidental":0,"velocity":127},{"type":"note","time":0,"duration":1.9979166666666668,"noteValue":29,"track":2,"pitch":{"octave":3,"step":"D","alter":0},"accidental":0,"velocity":100},{"type":"note","time":0,"duration":1.9979166666666668,"noteValue":26,"track":2,"pitch":{"octave":3,"step":"B","alter":0},"accidental":0,"velocity":100},{"type":"note","time":0,"duration":0,"noteValue":22,"track":2,"pitch":{"octave":2,"step":"G","alter":0},"accidental":0,"velocity":100},{"type":"note","time":0,"duration":0.625,"noteValue":22,"track":3,"pitch":{"octave":2,"step":"G","alter":0},"accidental":0,"velocity":127},{"type":"note","time":0,"duration":0.625,"noteValue":17,"track":3,"pitch":{"octave":2,"step":"D","alter":0},"accidental":0,"velocity":127},{"type":"note","time":0,"duration":0.5,"noteValue":41,"track":4,"pitch":{"octave":4,"step":"D","alter":0},"accidental":0,"velocity":127},{"type":"note","time":0,"duration":0.5,"noteValue":38,"track":4,"pitch":{"octave":4,"step":"B","alter":0},"accidental":0,"velocity":127},{"type":"note","time":0,"duration":0.5,"noteValue":34,"track":4,"pitch":{"octave":3,"step":"G","alter":0},"accidental":0,"velocity":127},{"type":"note","time":0.5,"duration":0.24791666666666667,"noteValue":46,"track":1,"pitch":{"octave":4,"step":"G","alter":0},"accidental":0,"velocity":127},{"type":"note","time":0.75,"duration":0.24791666666666667,"noteValue":46,"track":1,"pitch":{"octave":4,"step":"G","alter":0},"accidental":0,"velocity":127},{"type":"note","time":0.75,"duration":0,"noteValue":22,"track":3,"pitch":{"octave":2,"step":"G","alter":0},"accidental":0,"velocity":127},{"type":"note","time":0.75,"duration":0,"noteValue":17,"track":3,"pitch":{"octave":2,"step":"D","alter":0},"accidental":0,"velocity":127},{"type":"note","time":1,"duration":0.4979166666666668,"noteValue":46,"track":1,"pitch":{"octave":4,"step":"G","alter":0},"accidental":0,"velocity":127},{"type":"note","time":1,"duration":0,"noteValue":17,"track":3,"pitch":{"octave":2,"step":"D","alter":0},"accidental":0,"velocity":127},{"type":"note","time":1,"duration":0,"noteValue":22,"track":3,"pitch":{"octave":2,"step":"G","alter":0},"accidental":0,"velocity":127},{"type":"note","time":1.5000000000000002,"duration":0.24791666666666656,"noteValue":46,"track":1,"pitch":{"octave":4,"step":"G","alter":0},"accidental":0,"velocity":127},{"type":"note","time":1.7500000000000002,"duration":0.24791666666666656,"noteValue":46,"track":1,"pitch":{"octave":4,"step":"G","alter":0},"accidental":0,"velocity":127},{"type":"note","time":2,"duration":0.4979166666666668,"noteValue":50,"track":1,"pitch":{"octave":5,"step":"B","alter":0},"accidental":0,"velocity":127},{"type":"note","time":2,"duration":1.9979166666666668,"noteValue":26,"track":2,"pitch":{"octave":3,"step":"B","alter":0},"accidental":0,"velocity":100},{"type":"note","time":2,"duration":0,"noteValue":22,"track":2,"pitch":{"octave":2,"step":"G","alter":0},"accidental":0,"velocity":100},{"type":"note","time":2,"duration":1.9979166666666668,"noteValue":29,"track":2,"pitch":{"octave":3,"step":"D","alter":0},"accidental":0,"velocity":100},{"type":"note","time":2,"duration":0,"noteValue":17,"track":3,"pitch":{"octave":2,"step":"D","alter":0},"accidental":0,"velocity":127},{"type":"note","time":2,"duration":0,"noteValue":22,"track":3,"pitch":{"octave":2,"step":"G","alter":0},"accidental":0,"velocity":127},{"type":"note","time":2,"duration":0.5,"noteValue":38,"track":4,"pitch":{"octave":4,"step":"B","alter":0},"accidental":0,"velocity":127},{"type":"note","time":2,"duration":0.5,"noteValue":34,"track":4,"pitch":{"octave":3,"step":"G","alter":0},"accidental":0,"velocity":127},{"type":"note","time":2,"duration":0.5,"noteValue":41,"track":4,"pitch":{"octave":4,"step":"D","alter":0},"accidental":0,"velocity":127},{"type":"note","time":2.5,"duration":0.24791666666666679,"noteValue":53,"track":1,"pitch":{"octave":5,"step":"D","alter":0},"accidental":0,"velocity":127},{"type":"note","time":2.75,"duration":0.24791666666666679,"noteValue":53,"track":1,"pitch":{"octave":5,"step":"D","alter":0},"accidental":0,"velocity":127},{"type":"note","time":2.75,"duration":0,"noteValue":22,"track":3,"pitch":{"octave":2,"step":"G","alter":0},"accidental":0,"velocity":127},{"type":"note","time":2.75,"duration":0,"noteValue":17,"track":3,"pitch":{"octave":2,"step":"D","alter":0},"accidental":0,"velocity":127},{"type":"note","time":3,"duration":0.4979166666666668,"noteValue":50,"track":1,"pitch":{"octave":5,"step":"B","alter":0},"accidental":0,"velocity":127},{"type":"note","time":3,"duration":0,"noteValue":17,"track":3,"pitch":{"octave":2,"step":"D","alter":0},"accidental":0,"velocity":127},{"type":"note","time":3,"duration":0,"noteValue":22,"track":3,"pitch":{"octave":2,"step":"G","alter":0},"accidental":0,"velocity":127},{"type":"note","time":3.5,"duration":0.4979166666666668,"noteValue":46,"track":1,"pitch":{"octave":4,"step":"G","alter":0},"accidental":0,"velocity":127},{"type":"note","time":4,"duration":0.4979166666666668,"noteValue":48,"track":1,"pitch":{"octave":5,"step":"A","alter":0},"accidental":0,"velocity":127},{"type":"note","time":4,"duration":1.9979166666666668,"noteValue":27,"track":2,"pitch":{"octave":3,"step":"C","alter":0},"accidental":0,"velocity":100},{"type":"note","time":4,"duration":1.9979166666666668,"noteValue":21,"track":2,"pitch":{"octave":2,"step":"F","alter":1},"accidental":1,"velocity":100},{"type":"note","time":4,"duration":1.9979166666666668,"noteValue":29,"track":2,"pitch":{"octave":3,"step":"D","alter":0},"accidental":0,"velocity":100},{"type":"note","time":4,"duration":0.6875,"noteValue":24,"track":3,"pitch":{"octave":3,"step":"A","alter":0},"accidental":0,"velocity":127},{"type":"note","time":4,"duration":0.6875,"noteValue":17,"track":3,"pitch":{"octave":2,"step":"D","alter":0},"accidental":0,"velocity":127},{"type":"note","time":4,"duration":0.5,"noteValue":39,"track":4,"pitch":{"octave":4,"step":"C","alter":0},"accidental":0,"velocity":127},{"type":"note","time":4,"duration":0.5,"noteValue":33,"track":4,"pitch":{"octave":3,"step":"F","alter":1},"accidental":1,"velocity":127},{"type":"note","time":4,"duration":0.5,"noteValue":41,"track":4,"pitch":{"octave":4,"step":"D","alter":0},"accidental":0,"velocity":127},{"type":"note","time":4.5,"duration":0.24791666666666679,"noteValue":48,"track":1,"pitch":{"octave":5,"step":"A","alter":0},"accidental":0,"velocity":127},{"type":"note","time":4.75,"duration":0.24791666666666679,"noteValue":48,"track":1,"pitch":{"octave":5,"step":"A","alter":0},"accidental":0,"velocity":127},{"type":"note","time":4.75,"duration":0,"noteValue":24,"track":3,"pitch":{"octave":3,"step":"A","alter":0},"accidental":0,"velocity":127},{"type":"note","time":4.75,"duration":0,"noteValue":17,"track":3,"pitch":{"octave":2,"step":"D","alter":0},"accidental":0,"velocity":127},{"type":"note","time":5,"duration":0.4979166666666668,"noteValue":48,"track":1,"pitch":{"octave":5,"step":"A","alter":0},"accidental":0,"velocity":127},{"type":"note","time":5,"duration":0,"noteValue":24,"track":3,"pitch":{"octave":3,"step":"A","alter":0},"accidental":0,"velocity":127},{"type":"note","time":5,"duration":0,"noteValue":17,"track":3,"pitch":{"octave":2,"step":"D","alter":0},"accidental":0,"velocity":127},{"type":"note","time":5.5,"duration":0.24791666666666679,"noteValue":48,"track":1,"pitch":{"octave":5,"step":"A","alter":0},"accidental":0,"velocity":127},{"type":"note","time":5.75,"duration":0.24791666666666679,"noteValue":48,"track":1,"pitch":{"octave":5,"step":"A","alter":0},"accidental":0,"velocity":127},{"type":"note","time":6,"duration":0.4979166666666668,"noteValue":45,"track":1,"pitch":{"octave":4,"step":"F","alter":1},"accidental":1,"velocity":127},{"type":"note","time":6,"duration":1.9979166666666668,"noteValue":27,"track":2,"pitch":{"octave":3,"step":"C","alter":0},"accidental":0,"velocity":100},{"type":"note","time":6,"duration":1.9979166666666668,"noteValue":21,"track":2,"pitch":{"octave":2,"step":"F","alter":1},"accidental":1,"velocity":100},{"type":"note","time":6,"duration":1.9979166666666668,"noteValue":29,"track":2,"pitch":{"octave":3,"step":"D","alter":0},"accidental":0,"velocity":100},{"type":"note","time":6,"duration":0,"noteValue":24,"track":3,"pitch":{"octave":3,"step":"A","alter":0},"accidental":0,"velocity":127},{"type":"note","time":6,"duration":0,"noteValue":17,"track":3,"pitch":{"octave":2,"step":"D","alter":0},"accidental":0,"velocity":127},{"type":"note","time":6,"duration":0.5,"noteValue":39,"track":4,"pitch":{"octave":4,"step":"C","alter":0},"accidental":0,"velocity":127},{"type":"note","time":6,"duration":0.5,"noteValue":33,"track":4,"pitch":{"octave":3,"step":"F","alter":1},"accidental":1,"velocity":127},{"type":"note","time":6,"duration":0.5,"noteValue":41,"track":4,"pitch":{"octave":4,"step":"D","alter":0},"accidental":0,"velocity":127},{"type":"note","time":6.5,"duration":0.24791666666666679,"noteValue":48,"track":1,"pitch":{"octave":5,"step":"A","alter":0},"accidental":0,"velocity":127},{"type":"note","time":6.75,"duration":0.24791666666666679,"noteValue":48,"track":1,"pitch":{"octave":5,"step":"A","alter":0},"accidental":0,"velocity":127},{"type":"note","time":6.75,"duration":0,"noteValue":24,"track":3,"pitch":{"octave":3,"step":"A","alter":0},"accidental":0,"velocity":127},{"type":"note","time":6.75,"duration":0,"noteValue":17,"track":3,"pitch":{"octave":2,"step":"D","alter":0},"accidental":0,"velocity":127},{"type":"note","time":7,"duration":0.4979166666666668,"noteValue":45,"track":1,"pitch":{"octave":4,"step":"F","alter":1},"accidental":1,"velocity":127},{"type":"note","time":7,"duration":0,"noteValue":24,"track":3,"pitch":{"octave":3,"step":"A","alter":0},"accidental":0,"velocity":127},{"type":"note","time":7,"duration":0,"noteValue":17,"track":3,"pitch":{"octave":2,"step":"D","alter":0},"accidental":0,"velocity":127},{"type":"note","time":7.5,"duration":0.4979166666666668,"noteValue":41,"track":1,"pitch":{"octave":4,"step":"D","alter":0},"accidental":0,"velocity":127},{"type":"note","time":8,"duration":0.4979166666666668,"noteValue":46,"track":1,"pitch":{"octave":4,"step":"G","alter":0},"accidental":0,"velocity":127},{"type":"note","time":8,"duration":1.9979166666666668,"noteValue":26,"track":2,"pitch":{"octave":3,"step":"B","alter":0},"accidental":0,"velocity":100},{"type":"note","time":8,"duration":1.9979166666666668,"noteValue":29,"track":2,"pitch":{"octave":3,"step":"D","alter":0},"accidental":0,"velocity":100},{"type":"note","time":8,"duration":0,"noteValue":22,"track":2,"pitch":{"octave":2,"step":"G","alter":0},"accidental":0,"velocity":100},{"type":"note","time":8,"duration":0,"noteValue":17,"track":3,"pitch":{"octave":2,"step":"D","alter":0},"accidental":0,"velocity":127},{"type":"note","time":8,"duration":0,"noteValue":22,"track":3,"pitch":{"octave":2,"step":"G","alter":0},"accidental":0,"velocity":127},{"type":"note","time":8,"duration":0.5,"noteValue":38,"track":4,"pitch":{"octave":4,"step":"B","alter":0},"accidental":0,"velocity":127},{"type":"note","time":8,"duration":0.5,"noteValue":41,"track":4,"pitch":{"octave":4,"step":"D","alter":0},"accidental":0,"velocity":127},{"type":"note","time":8,"duration":0.5,"noteValue":34,"track":4,"pitch":{"octave":3,"step":"G","alter":0},"accidental":0,"velocity":127},{"type":"note","time":8,"duration":0.22916666666666607,"noteValue":17,"track":5,"pitch":{"octave":2,"step":"D","alter":0},"accidental":0,"velocity":127},{"type":"note","time":8,"duration":0.22916666666666607,"noteValue":22,"track":5,"pitch":{"octave":2,"step":"G","alter":0},"accidental":0,"velocity":127},{"type":"note","time":8.5,"duration":0.24791666666666679,"noteValue":46,"track":1,"pitch":{"octave":4,"step":"G","alter":0},"accidental":0,"velocity":127},{"type":"note","time":8.729166666666666,"duration":0,"noteValue":22,"track":5,"pitch":{"octave":2,"step":"G","alter":0},"accidental":0,"velocity":127},{"type":"note","time":8.729166666666666,"duration":0,"noteValue":17,"track":5,"pitch":{"octave":2,"step":"D","alter":0},"accidental":0,"velocity":127},{"type":"note","time":8.75,"duration":0.24791666666666679,"noteValue":46,"track":1,"pitch":{"octave":4,"step":"G","alter":0},"accidental":0,"velocity":127},{"type":"note","time":8.75,"duration":0,"noteValue":22,"track":3,"pitch":{"octave":2,"step":"G","alter":0},"accidental":0,"velocity":127},{"type":"note","time":8.75,"duration":0,"noteValue":17,"track":3,"pitch":{"octave":2,"step":"D","alter":0},"accidental":0,"velocity":127},{"type":"note","time":8.979166666666666,"duration":0,"noteValue":22,"track":5,"pitch":{"octave":2,"step":"G","alter":0},"accidental":0,"velocity":127},{"type":"note","time":8.979166666666666,"duration":0,"noteValue":17,"track":5,"pitch":{"octave":2,"step":"D","alter":0},"accidental":0,"velocity":127},{"type":"note","time":9,"duration":0.4979166666666668,"noteValue":46,"track":1,"pitch":{"octave":4,"step":"G","alter":0},"accidental":0,"velocity":127},{"type":"note","time":9,"duration":0,"noteValue":22,"track":3,"pitch":{"octave":2,"step":"G","alter":0},"accidental":0,"velocity":127},{"type":"note","time":9,"duration":0,"noteValue":17,"track":3,"pitch":{"octave":2,"step":"D","alter":0},"accidental":0,"velocity":127},{"type":"note","time":9.5,"duration":0.24791666666666679,"noteValue":46,"track":1,"pitch":{"octave":4,"step":"G","alter":0},"accidental":0,"velocity":127},{"type":"note","time":9.75,"duration":0.24791666666666679,"noteValue":46,"track":1,"pitch":{"octave":4,"step":"G","alter":0},"accidental":0,"velocity":127},{"type":"note","time":9.979166666666666,"duration":0,"noteValue":17,"track":5,"pitch":{"octave":2,"step":"D","alter":0},"accidental":0,"velocity":127},{"type":"note","time":9.979166666666666,"duration":0.01875000000000071,"noteValue":22,"track":5,"pitch":{"octave":2,"step":"G","alter":0},"accidental":0,"velocity":127},{"type":"note","time":10,"duration":0.4979166666666668,"noteValue":50,"track":1,"pitch":{"octave":5,"step":"B","alter":0},"accidental":0,"velocity":127},{"type":"note","time":10,"duration":0,"noteValue":22,"track":2,"pitch":{"octave":2,"step":"G","alter":0},"accidental":0,"velocity":100},{"type":"note","time":10,"duration":1.9979166666666668,"noteValue":26,"track":2,"pitch":{"octave":3,"step":"B","alter":0},"accidental":0,"velocity":100},{"type":"note","time":10,"duration":1.9979166666666668,"noteValue":29,"track":2,"pitch":{"octave":3,"step":"D","alter":0},"accidental":0,"velocity":100},{"type":"note","time":10,"duration":0,"noteValue":17,"track":3,"pitch":{"octave":2,"step":"D","alter":0},"accidental":0,"velocity":127},{"type":"note","time":10,"duration":0,"noteValue":22,"track":3,"pitch":{"octave":2,"step":"G","alter":0},"accidental":0,"velocity":127},{"type":"note","time":10,"duration":0.5,"noteValue":34,"track":4,"pitch":{"octave":3,"step":"G","alter":0},"accidental":0,"velocity":127},{"type":"note","time":10,"duration":0.5,"noteValue":38,"track":4,"pitch":{"octave":4,"step":"B","alter":0},"accidental":0,"velocity":127},{"type":"note","time":10,"duration":0.5,"noteValue":41,"track":4,"pitch":{"octave":4,"step":"D","alter":0},"accidental":0,"velocity":127},{"type":"note","time":10.5,"duration":0.24791666666666679,"noteValue":53,"track":1,"pitch":{"octave":5,"step":"D","alter":0},"accidental":0,"velocity":127},{"type":"note","time":10.729166666666666,"duration":0,"noteValue":22,"track":5,"pitch":{"octave":2,"step":"G","alter":0},"accidental":0,"velocity":127},{"type":"note","time":10.729166666666666,"duration":0,"noteValue":17,"track":5,"pitch":{"octave":2,"step":"D","alter":0},"accidental":0,"velocity":127},{"type":"note","time":10.75,"duration":0.24791666666666679,"noteValue":53,"track":1,"pitch":{"octave":5,"step":"D","alter":0},"accidental":0,"velocity":127},{"type":"note","time":10.75,"duration":0,"noteValue":22,"track":3,"pitch":{"octave":2,"step":"G","alter":0},"accidental":0,"velocity":127},{"type":"note","time":10.75,"duration":0,"noteValue":17,"track":3,"pitch":{"octave":2,"step":"D","alter":0},"accidental":0,"velocity":127},{"type":"note","time":10.979166666666666,"duration":0,"noteValue":22,"track":5,"pitch":{"octave":2,"step":"G","alter":0},"accidental":0,"velocity":127},{"type":"note","time":10.979166666666666,"duration":0,"noteValue":17,"track":5,"pitch":{"octave":2,"step":"D","alter":0},"accidental":0,"velocity":127},{"type":"note","time":11,"duration":0.4979166666666668,"noteValue":50,"track":1,"pitch":{"octave":5,"step":"B","alter":0},"accidental":0,"velocity":127},{"type":"note","time":11,"duration":0,"noteValue":22,"track":3,"pitch":{"octave":2,"step":"G","alter":0},"accidental":0,"velocity":127},{"type":"note","time":11,"duration":0,"noteValue":17,"track":3,"pitch":{"octave":2,"step":"D","alter":0},"accidental":0,"velocity":127},{"type":"note","time":11.5,"duration":0.4979166666666668,"noteValue":46,"track":1,"pitch":{"octave":4,"step":"G","alter":0},"accidental":0,"velocity":127},{"type":"note","time":11.979166666666666,"duration":0,"noteValue":24,"track":5,"pitch":{"octave":3,"step":"A","alter":0},"accidental":0,"velocity":127},{"type":"note","time":11.979166666666666,"duration":0,"noteValue":17,"track":5,"pitch":{"octave":2,"step":"D","alter":0},"accidental":0,"velocity":127},{"type":"note","time":12,"duration":0.4979166666666668,"noteValue":53,"track":1,"pitch":{"octave":5,"step":"D","alter":0},"accidental":0,"velocity":127},{"type":"note","time":12,"duration":1.9979166666666668,"noteValue":21,"track":2,"pitch":{"octave":2,"step":"F","alter":1},"accidental":1,"velocity":100},{"type":"note","time":12,"duration":1.9979166666666668,"noteValue":27,"track":2,"pitch":{"octave":3,"step":"C","alter":0},"accidental":0,"velocity":100},{"type":"note","time":12,"duration":1.9979166666666668,"noteValue":29,"track":2,"pitch":{"octave":3,"step":"D","alter":0},"accidental":0,"velocity":100},{"type":"note","time":12,"duration":0.22916666666666607,"noteValue":24,"track":3,"pitch":{"octave":3,"step":"A","alter":0},"accidental":0,"velocity":127},{"type":"note","time":12,"duration":0,"noteValue":17,"track":3,"pitch":{"octave":2,"step":"D","alter":0},"accidental":0,"velocity":127},{"type":"note","time":12,"duration":0.5,"noteValue":33,"track":4,"pitch":{"octave":3,"step":"F","alter":1},"accidental":1,"velocity":127},{"type":"note","time":12,"duration":0.5,"noteValue":39,"track":4,"pitch":{"octave":4,"step":"C","alter":0},"accidental":0,"velocity":127},{"type":"note","time":12,"duration":0.5,"noteValue":41,"track":4,"pitch":{"octave":4,"step":"D","alter":0},"accidental":0,"velocity":127},{"type":"note","time":12.5,"duration":0.24791666666666679,"noteValue":51,"track":1,"pitch":{"octave":5,"step":"C","alter":0},"accidental":0,"velocity":127},{"type":"note","time":12.729166666666666,"duration":0,"noteValue":24,"track":5,"pitch":{"octave":3,"step":"A","alter":0},"accidental":0,"velocity":127},{"type":"note","time":12.729166666666666,"duration":0,"noteValue":17,"track":5,"pitch":{"octave":2,"step":"D","alter":0},"accidental":0,"velocity":127},{"type":"note","time":12.75,"duration":0.24791666666666679,"noteValue":51,"track":1,"pitch":{"octave":5,"step":"C","alter":0},"accidental":0,"velocity":127},{"type":"note","time":12.75,"duration":0,"noteValue":24,"track":3,"pitch":{"octave":3,"step":"A","alter":0},"accidental":0,"velocity":127},{"type":"note","time":12.75,"duration":0,"noteValue":17,"track":3,"pitch":{"octave":2,"step":"D","alter":0},"accidental":0,"velocity":127},{"type":"note","time":12.979166666666666,"duration":0,"noteValue":17,"track":5,"pitch":{"octave":2,"step":"D","alter":0},"accidental":0,"velocity":127},{"type":"note","time":12.979166666666666,"duration":0,"noteValue":24,"track":5,"pitch":{"octave":3,"step":"A","alter":0},"accidental":0,"velocity":127},{"type":"note","time":13,"duration":0.4979166666666668,"noteValue":50,"track":1,"pitch":{"octave":5,"step":"B","alter":0},"accidental":0,"velocity":127},{"type":"note","time":13,"duration":0,"noteValue":17,"track":3,"pitch":{"octave":2,"step":"D","alter":0},"accidental":0,"velocity":127},{"type":"note","time":13,"duration":0,"noteValue":24,"track":3,"pitch":{"octave":3,"step":"A","alter":0},"accidental":0,"velocity":127},{"type":"note","time":13.5,"duration":0.4979166666666668,"noteValue":48,"track":1,"pitch":{"octave":5,"step":"A","alter":0},"accidental":0,"velocity":127},{"type":"note","time":14,"duration":0,"noteValue":46,"track":1,"pitch":{"octave":4,"step":"G","alter":0},"accidental":0,"velocity":127},{"type":"note","time":14,"duration":0,"noteValue":22,"track":2,"pitch":{"octave":2,"step":"G","alter":0},"accidental":0,"velocity":100},{"type":"note","time":14,"duration":1.4979166666666668,"noteValue":26,"track":2,"pitch":{"octave":3,"step":"B","alter":0},"accidental":0,"velocity":100},{"type":"note","time":14,"duration":0,"noteValue":29,"track":2,"pitch":{"octave":3,"step":"D","alter":0},"accidental":0,"velocity":100},{"type":"note","time":14,"duration":0,"noteValue":17,"track":3,"pitch":{"octave":2,"step":"D","alter":0},"accidental":0,"velocity":127},{"type":"note","time":14,"duration":1.4979166666666668,"noteValue":22,"track":3,"pitch":{"octave":2,"step":"G","alter":0},"accidental":0,"velocity":127},{"type":"note","time":14,"duration":2,"noteValue":34,"track":6,"pitch":{"octave":3,"step":"G","alter":0},"accidental":0,"velocity":127},{"type":"note","time":14,"duration":1.4979166666666668,"noteValue":29,"track":6,"pitch":{"octave":3,"step":"D","alter":0},"accidental":0,"velocity":127},{"type":"note","time":14,"duration":1.4979166666666668,"noteValue":46,"track":6,"pitch":{"octave":4,"step":"G","alter":0},"accidental":0,"velocity":127},{"type":"note","time":14,"duration":2,"noteValue":41,"track":6,"pitch":{"octave":4,"step":"D","alter":0},"accidental":0,"velocity":127}],"tracks":{"1":{"instrument":"piano","name":"R.H. Student   "},"2":{"instrument":"piano","name":"L.H. Student   "},"3":{"instrument":"piano","name":"BASS           "},"4":{"instrument":"piano","name":"Vibes          "},"5":{"instrument":"piano","name":"Low Horns      "},"6":{"instrument":"piano","name":"Syntar         "}},"bpms":[{"time":0,"bpm":240}],"timeSignature":{"type":"meta","subType":"timeSignature","typeByte":255,"subTypeByte":88,"deltaTime":0,"numerator":4,"denominator":4,"metronome":24,"thirtySeconds":8}}